tagpro_eu/__init__.py
tagpro_eu/blob.py
tagpro_eu/bulk.py
tagpro_eu/constants.py
tagpro_eu/data.py
tagpro_eu/map.py
tagpro_eu/match.py
tagpro_eu/player.py
tagpro_eu/util.py
tagpro_eu/web.py
test/__init__.py
test/test_blob.py
test/test_core.py
test/test_util.py
tagpro_eu-1.1.2.dist-info/LICENSE.txt
tagpro_eu-1.1.2.dist-info/METADATA
tagpro_eu-1.1.2.dist-info/WHEEL
tagpro_eu-1.1.2.dist-info/top_level.txt
tagpro_eu-1.1.2.dist-info/RECORD
