Metadata-Version: 2.1
Name: tagpro-eu
Version: 1.1.2
Summary: A Python parser for tagpro.eu matches
Home-page: https://github.com/arfie/tagpro-eu-python
Author: Ruud Verbeek
License: GPL-3.0
Keywords: tagpro
Platform: UNKNOWN
Classifier: Development Status :: 4 - Beta
Classifier: License :: OSI Approved :: GNU General Public License v3 or later (GPLv3+)
Classifier: Programming Language :: Python :: 3.6
Classifier: Topic :: Games/Entertainment
Requires-Python: >=3.6
Requires-Dist: requests
